LICENSE
README.md
setup.py
brainsurf/__init__.py
brainsurf.egg-info/PKG-INFO
brainsurf.egg-info/SOURCES.txt
brainsurf.egg-info/dependency_links.txt
brainsurf.egg-info/requires.txt
brainsurf.egg-info/top_level.txt
brainsurf/analysis/__init__.py
brainsurf/analysis/corelation_analysis.py
brainsurf/analysis/erp_analysis.py
brainsurf/analysis/frequency.py
brainsurf/analysis/multi_fractal.py
brainsurf/analysis/power_spectrum.py
brainsurf/analysis/stats_analysis.py
brainsurf/cognitive/__init__.py
brainsurf/cognitive/cognitive_comparision.py
brainsurf/cognitive/cognitive_indexes.py
brainsurf/io/__init__.py
brainsurf/io/csv.py
brainsurf/io/df.py
brainsurf/io/edf.py
brainsurf/io/eeg_data.py
brainsurf/io/mff.py
brainsurf/io/xlsx.py
brainsurf/machine_learning/__init__.py
brainsurf/machine_learning/eeg_binary_classification.py
brainsurf/machine_learning/rnn_module.py
brainsurf/machine_learning/time_series.py
brainsurf/preprocessing/__init__.py
brainsurf/preprocessing/artifact_removal.py
brainsurf/preprocessing/baseline.py
brainsurf/preprocessing/epoching.py
brainsurf/preprocessing/filtering.py
brainsurf/utils/__init__.py
brainsurf/utils/data.py
brainsurf/utils/performance.py
brainsurf/visualization/__init__.py
brainsurf/visualization/comparative_visualize.py
brainsurf/visualization/eeg_data_visualization.py
brainsurf/visualization/plot_cluster.py
brainsurf/visualization/plot_coherence.py
brainsurf/visualization/plot_correlation.py
brainsurf/visualization/plot_eeg_signal.py
brainsurf/visualization/plot_heatmap.py
brainsurf/visualization/plot_power_spectrum.py
brainsurf/visualization/plot_spectogram.py
brainsurf/visualization/plot_time_series.py
brainsurf/visualization/plot_topomap.py