Metadata-Version: 2.1
Name: brainsurf
Version: 7.0.0
Summary: EEG Signal Processing Library
Home-page: https://github.com/preethihiremath/brainsurf
Author: preethivhiremath
Author-email: preethivhiremath.vh@gmail.com
License: UNKNOWN
Platform: UNKNOWN
Classifier: Development Status :: 3 - Alpha
Classifier: Intended Audience :: Developers
Classifier: Intended Audience :: Science/Research
Classifier: Operating System :: OS Independent
Classifier: Programming Language :: Python :: 3
Classifier: Programming Language :: Python :: 3.6
Classifier: Programming Language :: Python :: 3.7
Classifier: Programming Language :: Python :: 3.8
Classifier: Programming Language :: Python :: 3.9
Classifier: Topic :: Scientific/Engineering :: Medical Science Apps.
License-File: LICENSE
